nosytx/__init__.py
nosytx/nosytx.py
nosytx-1.0.1.dist-info/METADATA
nosytx-1.0.1.dist-info/WHEEL
nosytx-1.0.1.dist-info/top_level.txt
nosytx-1.0.1.dist-info/RECORD
