Metadata-Version: 2.1
Name: nosytx
Version: 1.0.1
Summary: A Library for the nosytx.eu Image API
Author: Erik05Master
Author-email: <info@sytxlabs.eu>
Keywords: python,api
Requires-Dist: aiohttp
